odoo/addons/l10n_de_toponyms/README.rst
odoo/addons/l10n_de_toponyms/__init__.py
odoo/addons/l10n_de_toponyms/__manifest__.py
odoo/addons/l10n_de_toponyms/i18n/de.po
odoo/addons/l10n_de_toponyms/i18n/l10n_de_toponyms.pot
odoo/addons/l10n_de_toponyms/security/ir.model.access.csv
odoo/addons/l10n_de_toponyms/static/description/icon.png
odoo/addons/l10n_de_toponyms/tests/__init__.py
odoo/addons/l10n_de_toponyms/tests/test_l10n_de_toponyms.py
odoo/addons/l10n_de_toponyms/wizard/__init__.py
odoo/addons/l10n_de_toponyms/wizard/geonames_import.py
odoo/addons/l10n_de_toponyms/wizard/l10n_de_toponyms_wizard.py
odoo/addons/l10n_de_toponyms/wizard/l10n_de_toponyms_wizard.xml
odoo14_addon_l10n_de_toponyms-14.0.1.0.1.dist-info/METADATA
odoo14_addon_l10n_de_toponyms-14.0.1.0.1.dist-info/WHEEL
odoo14_addon_l10n_de_toponyms-14.0.1.0.1.dist-info/top_level.txt
odoo14_addon_l10n_de_toponyms-14.0.1.0.1.dist-info/RECORD
